native/apriltag/_init_robotpy_native_apriltag.py
native/apriltag/robotpy-native-apriltag.pc
native/apriltag/include/apriltag.h
native/apriltag/include/apriltag_math.h
native/apriltag/include/apriltag_pose.h
native/apriltag/include/tag16h5.h
native/apriltag/include/tag36h11.h
native/apriltag/include/common/debug_print.h
native/apriltag/include/common/doubles.h
native/apriltag/include/common/doubles_floats_impl.h
native/apriltag/include/common/floats.h
native/apriltag/include/common/g2d.h
native/apriltag/include/common/homography.h
native/apriltag/include/common/image_types.h
native/apriltag/include/common/image_u8.h
native/apriltag/include/common/image_u8x3.h
native/apriltag/include/common/image_u8x4.h
native/apriltag/include/common/matd.h
native/apriltag/include/common/math_util.h
native/apriltag/include/common/pam.h
native/apriltag/include/common/pjpeg.h
native/apriltag/include/common/pnm.h
native/apriltag/include/common/pthreads_cross.h
native/apriltag/include/common/string_util.h
native/apriltag/include/common/svd22.h
native/apriltag/include/common/time_util.h
native/apriltag/include/common/timeprofile.h
native/apriltag/include/common/unionfind.h
native/apriltag/include/common/workerpool.h
native/apriltag/include/common/zarray.h
native/apriltag/include/common/zhash.h
native/apriltag/include/common/zmaxheap.h
native/apriltag/include/frc/apriltag/AprilTag.h
native/apriltag/include/frc/apriltag/AprilTagDetection.h
native/apriltag/include/frc/apriltag/AprilTagDetector.h
native/apriltag/include/frc/apriltag/AprilTagDetector_cv.h
native/apriltag/include/frc/apriltag/AprilTagFieldLayout.h
native/apriltag/include/frc/apriltag/AprilTagFields.h
native/apriltag/include/frc/apriltag/AprilTagPoseEstimate.h
native/apriltag/include/frc/apriltag/AprilTagPoseEstimator.h
native/apriltag/include/test/getline.h
native/apriltag/lib/libapriltag.so
robotpy_native_apriltag-2025.3.2.dist-info/METADATA
robotpy_native_apriltag-2025.3.2.dist-info/WHEEL
robotpy_native_apriltag-2025.3.2.dist-info/entry_points.txt
robotpy_native_apriltag-2025.3.2.dist-info/RECORD
