Metadata-Version: 2.4
Name: robotpy-native-apriltag
Version: 2025.3.2
Summary: WPILib AprilTag Library
License-Expression: BSD-3-Clause
Requires-Dist: robotpy-native-wpimath==2025.3.2
Requires-Dist: robotpy-native-wpiutil==2025.3.2
